tae_grader-1.0.9.data/scripts/taeg
taeg/__init__.py
taeg/__main__.py
taeg/argparser.py
taeg/run.py
taeg/utils.py
taeg/version.py
taeg/assign/__init__.py
taeg/assign/assignment.py
taeg/assign/cell_generators.py
taeg/assign/constants.py
taeg/assign/notebook_transformer.py
taeg/assign/output.py
taeg/assign/questions.py
taeg/assign/solutions.py
taeg/assign/tests.py
taeg/assign/utils.py
taeg/assign/r_adapter/__init__.py
taeg/assign/r_adapter/tests.py
taeg/assign/rmarkdown_adapter/__init__.py
taeg/assign/rmarkdown_adapter/constants.py
taeg/assign/rmarkdown_adapter/notebook_transformer.py
taeg/assign/rmarkdown_adapter/output.py
taeg/assign/rmarkdown_adapter/solutions.py
taeg/assign/rmarkdown_adapter/tests.py
taeg/assign/rmarkdown_adapter/utils.py
taeg/check/__init__.py
taeg/check/logs.py
taeg/check/notebook.py
taeg/execute/__init__.py
taeg/execute/check_wrapper.py
taeg/execute/execute_log.py
taeg/execute/execute_notebook.py
taeg/execute/execute_script.py
taeg/execute/results.py
taeg/export/__init__.py
taeg/export/exporters/__init__.py
taeg/export/exporters/base_exporter.py
taeg/export/exporters/utils.py
taeg/export/exporters/via_html.py
taeg/export/exporters/via_latex.py
taeg/export/exporters/templates/via_html.tpl
taeg/export/exporters/templates/via_latex.tpl
taeg/generate/__init__.py
taeg/generate/autograder.py
taeg/generate/constants.py
taeg/generate/token.py
taeg/generate/utils.py
taeg/generate/run_autograder/__init__.py
taeg/generate/run_autograder/run_autograder.py
taeg/generate/run_autograder/r_adapter/__init__.py
taeg/generate/run_autograder/r_adapter/run_autograder.py
taeg/generate/templates/environment.yml
taeg/generate/templates/requirements.r
taeg/generate/templates/requirements.txt
taeg/generate/templates/run_autograder
taeg/generate/templates/run_otter.py
taeg/generate/templates/setup.sh
taeg/grade/__init__.py
taeg/grade/__main__.py
taeg/grade/containers.py
taeg/grade/metadata.py
taeg/grade/utils.py
taeg/service/__init__.py
taeg/service/build.py
tae_grader-1.0.9.dist-info/LICENSE
tae_grader-1.0.9.dist-info/METADATA
tae_grader-1.0.9.dist-info/WHEEL
tae_grader-1.0.9.dist-info/top_level.txt
tae_grader-1.0.9.dist-info/RECORD
